MANIFEST.in
README.md
setup.py
di/__init__.py
di/di.py
py_di.egg-info/PKG-INFO
py_di.egg-info/SOURCES.txt
py_di.egg-info/dependency_links.txt
py_di.egg-info/top_level.txt