Metadata-Version: 1.1
Name: py-di
Version: 1.1
Summary: Container of Dependency Injection (IOC) implementation.
Home-page: https://github.com/moisespsena/py_di
Author: Moises P. Sena
Author-email: moisespsena@gmail.com
License: BSD
Keywords: utils utilities di dependecy injection ioc
Platform: UNKNOWN
Classifier: Development Status :: 5 - Production/Stable
Classifier: Topic :: Utilities
Classifier: Intended Audience :: Developers
Classifier: License :: OSI Approved :: BSD License
Classifier: Operating System :: OS Independent
Classifier: Programming Language :: Python :: 2.7
Classifier: Programming Language :: Python :: 3
